card91_business_sdk/__init__.py
card91_business_sdk/card91BusinessSDK.py
card91BusinessSDK-0.0.20.dist-info/METADATA
card91BusinessSDK-0.0.20.dist-info/WHEEL
card91BusinessSDK-0.0.20.dist-info/top_level.txt
card91BusinessSDK-0.0.20.dist-info/RECORD
