Metadata-Version: 2.1
Name: card91BusinessSDK
Version: 0.0.20
Summary: This package is used to access the bunch of Card91 fintech business services
Home-page: https://github.com/nk2909/Python-SDK.git
Author: Card91
Author-email: tech.apps@card91.io
Keywords: python
Classifier: Development Status :: 5 - Production/Stable
Classifier: Intended Audience :: Developers
Classifier: Operating System :: OS Independent
Requires-Dist: requests
